vizta/__init__.py
vizta/palettes.py
vizta/utils.py
vizta/version.py
vizta/mpl/__init__.py
vizta/mpl/themes.py
vizta-1.1.2.dist-info/licenses/LICENSE
vizta-1.1.2.dist-info/METADATA
vizta-1.1.2.dist-info/WHEEL
vizta-1.1.2.dist-info/top_level.txt
vizta-1.1.2.dist-info/RECORD
